Metadata-Version: 2.0
Name: odoo9-addon-survey-one-choice-per-column
Version: 9.0.1.0.0
Summary: Adds a new option 'One Choice Per Column' to matrix types.
Home-page: http://www.onestein.eu
Author: Onestein, Odoo Community Association (OCA)
Author-email: support@odoo-community.org
License: AGPL-3
Platform: UNKNOWN
Classifier: Programming Language :: Python :: 2.7
Classifier: Framework :: Odoo
Classifier: License :: OSI Approved :: GNU Affero General Public License v3
Requires-Dist: odoo (<9.1a,>=9.0a)
